<?xml version="1.0" encoding="utf-8"?>
<name>
<values>Ripples</values>
<values-am>"ሞገዶች"</values-am>
<values-ar>"أمواج"</values-ar>
<values-as>"ঢৌ"</values-as>
<values-az>"Kiçik dalğalar"</values-az>
<values-jv-LATN>"Riak-riak"</values-jv-LATN>
<values-sr-LATN>"Talasi"</values-sr-LATN>
<values-be>"Рабізна"</values-be>
<values-bg>"Вълнички"</values-bg>
<values-bn>"মৃদু তরঙ্গ"</values-bn>
<values-bo-CN>"ཆུ་ཡི་རླབས་རིས།"</values-bo-CN>
<values-bs>"Mreškanje"</values-bs>
<values-ca>"Onades"</values-ca>
<values-cs>"Vlny"</values-cs>
<values-da>"Krusninger"</values-da>
<values-de>"Wellen"</values-de>
<values-el>"Κυματισμοί"</values-el>
<values-en-GB>"Ripples"</values-en-GB>
<values-es>"Ondas"</values-es>
<values-es-US>"Olas"</values-es-US>
<values-et>"Lained"</values-et>
<values-eu>"Olatu txikiak"</values-eu>
<values-fa>"موج‌ها"</values-fa>
<values-fi>"Väreet"</values-fi>
<values-fr>"Ondulations"</values-fr>
<values-gl>"Ondiñas"</values-gl>
<values-gu>"રિપલ્સ"</values-gu>
<values-hi>"लहरें"</values-hi>
<values-hr>"Valovi"</values-hr>
<values-hu>"Hullámok"</values-hu>
<values-in>"Riak"</values-in>
<values-it>"Cerchi"</values-it>
<values-iw>"גלים"</values-iw>
<values-ja>"さざ波"</values-ja>
<values-ka>"ტალღები"</values-ka>
<values-kk>"Шымырлану"</values-kk>
<values-km>"រលក"</values-km>
<values-kn>"ಸಣ್ಣ ಅಲೆಗಳು"</values-kn>
<values-ko>"물결"</values-ko>
<values-lo>"ຄື້ນນ້ອຍໆ"</values-lo>
<values-lt>"Raibuliai"</values-lt>
<values-lv>"Sīki vilnīši"</values-lv>
<values-mai>"लहर"</values-mai>
<values-mi>"Ngā ripo"</values-mi>
<values-mk>"Бранови"</values-mk>
<values-ml>"അലകൾ"</values-ml>
<values-mn>"Долгион"</values-mn>
<values-mr>"तरंग"</values-mr>
<values-ms>"Riak"</values-ms>
<values-my>"Ripples"</values-my>
<values-my-ZG>"Ripples"</values-my-ZG>
<values-nb>"Krusninger"</values-nb>
<values-ne>"रिप्पलहरू"</values-ne>
<values-nl>"Rimpelingen"</values-nl>
<values-or>"ରିପ୍ପଲେସ୍‌"</values-or>
<values-pa>"ਛੋਟੀਆਂ ਲਹਿਰਾਂ"</values-pa>
<values-pl>"Fale"</values-pl>
<values-pt>"Ondulações"</values-pt>
<values-pt-PT>"Ondulação"</values-pt-PT>
<values-ro>"Ondulații"</values-ro>
<values-ru>"Водная рябь"</values-ru>
<values-si>"රැළි"</values-si>
<values-sk>"Vlnky"</values-sk>
<values-sl>"Val"</values-sl>
<values-sr>"Таласи"</values-sr>
<values-sv>"Krusningar"</values-sv>
<values-sw>"Viwimbi"</values-sw>
<values-ta>"சிற்றலைகள்"</values-ta>
<values-te>"రిప్పిల్స్"</values-te>
<values-th>"ระลอกคลื่น"</values-th>
<values-tl>"Mga Ripple"</values-tl>
<values-tr>"Dalgalar"</values-tr>
<values-ug>"دولقۇن"</values-ug>
<values-uk>"Хвилі"</values-uk>
<values-ur>"لہریں"</values-ur>
<values-uz>"Mavjlanish"</values-uz>
<values-vi>"Gợn sóng"</values-vi>
<values-zh-CN>"水波涟漪"</values-zh-CN>
<values-zh-HK>"水波漣漪"</values-zh-HK>
<values-zh-TW>"水波漣漪"</values-zh-TW>
<values-zz-ZX>[PL_574559]_Ripples</values-zz-ZX>
</name>